<annotation>
	<folder>待处理图片</folder>
	<filename>IMG_5123.JPG</filename>
	<path>C:\Users\Lenovo\Desktop\待处理图片\IMG_5123.JPG</path>
	<source>
		<database>Unknown</database>
	</source>
	<size>
		<width>4032</width>
		<height>3024</height>
		<depth>3</depth>
	</size>
	<segmented>0</segmented>
	<object>
		<name>B</name>
		<pose>Unspecified</pose>
		<truncated>0</truncated>
		<difficult>0</difficult>
		<bndbox>
			<xmin>724</xmin>
			<ymin>1217</ymin>
			<xmax>888</xmax>
			<ymax>1417</ymax>
		</bndbox>
	</object>
	<object>
		<name>B</name>
		<pose>Unspecified</pose>
		<truncated>0</truncated>
		<difficult>0</difficult>
		<bndbox>
			<xmin>1201</xmin>
			<ymin>1121</ymin>
			<xmax>1340</xmax>
			<ymax>1276</ymax>
		</bndbox>
	</object>
	<object>
		<name>B</name>
		<pose>Unspecified</pose>
		<truncated>0</truncated>
		<difficult>0</difficult>
		<bndbox>
			<xmin>1591</xmin>
			<ymin>1024</ymin>
			<xmax>1698</xmax>
			<ymax>1137</ymax>
		</bndbox>
	</object>
	<object>
		<name>B</name>
		<pose>Unspecified</pose>
		<truncated>0</truncated>
		<difficult>0</difficult>
		<bndbox>
			<xmin>2027</xmin>
			<ymin>937</ymin>
			<xmax>2101</xmax>
			<ymax>1034</ymax>
		</bndbox>
	</object>
	<object>
		<name>R</name>
		<pose>Unspecified</pose>
		<truncated>0</truncated>
		<difficult>0</difficult>
		<bndbox>
			<xmin>2930</xmin>
			<ymin>951</ymin>
			<xmax>3012</xmax>
			<ymax>1050</ymax>
		</bndbox>
	</object>
	<object>
		<name>R</name>
		<pose>Unspecified</pose>
		<truncated>0</truncated>
		<difficult>0</difficult>
		<bndbox>
			<xmin>2748</xmin>
			<ymin>1045</ymin>
			<xmax>2871</xmax>
			<ymax>1171</ymax>
		</bndbox>
	</object>
	<object>
		<name>R</name>
		<pose>Unspecified</pose>
		<truncated>0</truncated>
		<difficult>0</difficult>
		<bndbox>
			<xmin>2781</xmin>
			<ymin>1248</ymin>
			<xmax>2963</xmax>
			<ymax>1450</ymax>
		</bndbox>
	</object>
	<object>
		<name>R</name>
		<pose>Unspecified</pose>
		<truncated>0</truncated>
		<difficult>0</difficult>
		<bndbox>
			<xmin>2847</xmin>
			<ymin>1340</ymin>
			<xmax>3032</xmax>
			<ymax>1583</ymax>
		</bndbox>
	</object>
	<object>
		<name>R</name>
		<pose>Unspecified</pose>
		<truncated>0</truncated>
		<difficult>0</difficult>
		<bndbox>
			<xmin>2938</xmin>
			<ymin>1610</ymin>
			<xmax>3227</xmax>
			<ymax>1958</ymax>
		</bndbox>
	</object>
</annotation>
