<annotation>
	<folder>xml</folder>
	<filename>IMG_20210429_103435.jpg</filename>
	<path>/home/gu/桌面/标注/顾竣文/xml/IMG_20210429_103435.jpg</path>
	<source>
		<database>Unknown</database>
	</source>
	<size>
		<width>4000</width>
		<height>3000</height>
		<depth>3</depth>
	</size>
	<segmented>0</segmented>
	<object>
		<name>R</name>
		<pose>Unspecified</pose>
		<truncated>0</truncated>
		<difficult>0</difficult>
		<bndbox>
			<xmin>655</xmin>
			<ymin>919</ymin>
			<xmax>777</xmax>
			<ymax>1050</ymax>
		</bndbox>
	</object>
	<object>
		<name>R</name>
		<pose>Unspecified</pose>
		<truncated>0</truncated>
		<difficult>0</difficult>
		<bndbox>
			<xmin>1113</xmin>
			<ymin>948</ymin>
			<xmax>1258</xmax>
			<ymax>1097</ymax>
		</bndbox>
	</object>
	<object>
		<name>R</name>
		<pose>Unspecified</pose>
		<truncated>0</truncated>
		<difficult>0</difficult>
		<bndbox>
			<xmin>1702</xmin>
			<ymin>998</ymin>
			<xmax>1869</xmax>
			<ymax>1193</ymax>
		</bndbox>
	</object>
	<object>
		<name>R</name>
		<pose>Unspecified</pose>
		<truncated>0</truncated>
		<difficult>0</difficult>
		<bndbox>
			<xmin>2029</xmin>
			<ymin>1082</ymin>
			<xmax>2245</xmax>
			<ymax>1314</ymax>
		</bndbox>
	</object>
	<object>
		<name>B</name>
		<pose>Unspecified</pose>
		<truncated>0</truncated>
		<difficult>0</difficult>
		<bndbox>
			<xmin>3241</xmin>
			<ymin>868</ymin>
			<xmax>3405</xmax>
			<ymax>1048</ymax>
		</bndbox>
	</object>
	<object>
		<name>B</name>
		<pose>Unspecified</pose>
		<truncated>0</truncated>
		<difficult>0</difficult>
		<bndbox>
			<xmin>1133</xmin>
			<ymin>838</ymin>
			<xmax>1231</xmax>
			<ymax>942</ymax>
		</bndbox>
	</object>
	<object>
		<name>B</name>
		<pose>Unspecified</pose>
		<truncated>0</truncated>
		<difficult>0</difficult>
		<bndbox>
			<xmin>1689</xmin>
			<ymin>832</ymin>
			<xmax>1779</xmax>
			<ymax>940</ymax>
		</bndbox>
	</object>
	<object>
		<name>B</name>
		<pose>Unspecified</pose>
		<truncated>0</truncated>
		<difficult>0</difficult>
		<bndbox>
			<xmin>2310</xmin>
			<ymin>852</ymin>
			<xmax>2435</xmax>
			<ymax>987</ymax>
		</bndbox>
	</object>
</annotation>
