<annotation>
	<folder>待处理图片</folder>
	<filename>IMG_5153.JPG</filename>
	<path>C:\Users\Lenovo\Desktop\待处理图片\IMG_5153.JPG</path>
	<source>
		<database>Unknown</database>
	</source>
	<size>
		<width>4032</width>
		<height>3024</height>
		<depth>3</depth>
	</size>
	<segmented>0</segmented>
	<object>
		<name>B</name>
		<pose>Unspecified</pose>
		<truncated>1</truncated>
		<difficult>0</difficult>
		<bndbox>
			<xmin>1</xmin>
			<ymin>1279</ymin>
			<xmax>80</xmax>
			<ymax>1405</ymax>
		</bndbox>
	</object>
	<object>
		<name>B</name>
		<pose>Unspecified</pose>
		<truncated>0</truncated>
		<difficult>0</difficult>
		<bndbox>
			<xmin>494</xmin>
			<ymin>1008</ymin>
			<xmax>607</xmax>
			<ymax>1145</ymax>
		</bndbox>
	</object>
	<object>
		<name>R</name>
		<pose>Unspecified</pose>
		<truncated>0</truncated>
		<difficult>0</difficult>
		<bndbox>
			<xmin>1720</xmin>
			<ymin>928</ymin>
			<xmax>1800</xmax>
			<ymax>1049</ymax>
		</bndbox>
	</object>
	<object>
		<name>R</name>
		<pose>Unspecified</pose>
		<truncated>0</truncated>
		<difficult>0</difficult>
		<bndbox>
			<xmin>1767</xmin>
			<ymin>1065</ymin>
			<xmax>1897</xmax>
			<ymax>1239</ymax>
		</bndbox>
	</object>
	<object>
		<name>R</name>
		<pose>Unspecified</pose>
		<truncated>0</truncated>
		<difficult>0</difficult>
		<bndbox>
			<xmin>2480</xmin>
			<ymin>1402</ymin>
			<xmax>2750</xmax>
			<ymax>1715</ymax>
		</bndbox>
	</object>
	<object>
		<name>R</name>
		<pose>Unspecified</pose>
		<truncated>0</truncated>
		<difficult>0</difficult>
		<bndbox>
			<xmin>2910</xmin>
			<ymin>1579</ymin>
			<xmax>3280</xmax>
			<ymax>1982</ymax>
		</bndbox>
	</object>
</annotation>
