<annotation>
	<folder>待处理图片</folder>
	<filename>IMG_5045.JPG</filename>
	<path>C:\Users\Lenovo\Desktop\待处理图片\IMG_5045.JPG</path>
	<source>
		<database>Unknown</database>
	</source>
	<size>
		<width>4032</width>
		<height>3024</height>
		<depth>3</depth>
	</size>
	<segmented>0</segmented>
	<object>
		<name>B</name>
		<pose>Unspecified</pose>
		<truncated>0</truncated>
		<difficult>0</difficult>
		<bndbox>
			<xmin>595</xmin>
			<ymin>1627</ymin>
			<xmax>795</xmax>
			<ymax>1895</ymax>
		</bndbox>
	</object>
	<object>
		<name>B</name>
		<pose>Unspecified</pose>
		<truncated>0</truncated>
		<difficult>0</difficult>
		<bndbox>
			<xmin>1288</xmin>
			<ymin>1376</ymin>
			<xmax>1456</xmax>
			<ymax>1560</ymax>
		</bndbox>
	</object>
	<object>
		<name>B</name>
		<pose>Unspecified</pose>
		<truncated>0</truncated>
		<difficult>0</difficult>
		<bndbox>
			<xmin>1902</xmin>
			<ymin>1215</ymin>
			<xmax>2006</xmax>
			<ymax>1341</ymax>
		</bndbox>
	</object>
	<object>
		<name>B</name>
		<pose>Unspecified</pose>
		<truncated>0</truncated>
		<difficult>0</difficult>
		<bndbox>
			<xmin>2150</xmin>
			<ymin>1123</ymin>
			<xmax>2231</xmax>
			<ymax>1220</ymax>
		</bndbox>
	</object>
	<object>
		<name>B</name>
		<pose>Unspecified</pose>
		<truncated>0</truncated>
		<difficult>0</difficult>
		<bndbox>
			<xmin>2281</xmin>
			<ymin>1085</ymin>
			<xmax>2352</xmax>
			<ymax>1172</ymax>
		</bndbox>
	</object>
	<object>
		<name>B</name>
		<pose>Unspecified</pose>
		<truncated>0</truncated>
		<difficult>0</difficult>
		<bndbox>
			<xmin>2387</xmin>
			<ymin>1041</ymin>
			<xmax>2450</xmax>
			<ymax>1115</ymax>
		</bndbox>
	</object>
	<object>
		<name>B</name>
		<pose>Unspecified</pose>
		<truncated>0</truncated>
		<difficult>0</difficult>
		<bndbox>
			<xmin>2586</xmin>
			<ymin>995</ymin>
			<xmax>2643</xmax>
			<ymax>1059</ymax>
		</bndbox>
	</object>
	<object>
		<name>R</name>
		<pose>Unspecified</pose>
		<truncated>0</truncated>
		<difficult>0</difficult>
		<bndbox>
			<xmin>3259</xmin>
			<ymin>977</ymin>
			<xmax>3324</xmax>
			<ymax>1045</ymax>
		</bndbox>
	</object>
	<object>
		<name>R</name>
		<pose>Unspecified</pose>
		<truncated>0</truncated>
		<difficult>0</difficult>
		<bndbox>
			<xmin>3178</xmin>
			<ymin>1022</ymin>
			<xmax>3264</xmax>
			<ymax>1102</ymax>
		</bndbox>
	</object>
	<object>
		<name>R</name>
		<pose>Unspecified</pose>
		<truncated>0</truncated>
		<difficult>0</difficult>
		<bndbox>
			<xmin>3275</xmin>
			<ymin>1087</ymin>
			<xmax>3380</xmax>
			<ymax>1188</ymax>
		</bndbox>
	</object>
	<object>
		<name>R</name>
		<pose>Unspecified</pose>
		<truncated>0</truncated>
		<difficult>0</difficult>
		<bndbox>
			<xmin>3332</xmin>
			<ymin>1109</ymin>
			<xmax>3425</xmax>
			<ymax>1218</ymax>
		</bndbox>
	</object>
	<object>
		<name>R</name>
		<pose>Unspecified</pose>
		<truncated>0</truncated>
		<difficult>0</difficult>
		<bndbox>
			<xmin>3421</xmin>
			<ymin>1157</ymin>
			<xmax>3533</xmax>
			<ymax>1281</ymax>
		</bndbox>
	</object>
	<object>
		<name>R</name>
		<pose>Unspecified</pose>
		<truncated>0</truncated>
		<difficult>0</difficult>
		<bndbox>
			<xmin>3479</xmin>
			<ymin>1269</ymin>
			<xmax>3639</xmax>
			<ymax>1438</ymax>
		</bndbox>
	</object>
	<object>
		<name>R</name>
		<pose>Unspecified</pose>
		<truncated>0</truncated>
		<difficult>0</difficult>
		<bndbox>
			<xmin>3469</xmin>
			<ymin>1450</ymin>
			<xmax>3687</xmax>
			<ymax>1686</ymax>
		</bndbox>
	</object>
	<object>
		<name>R</name>
		<pose>Unspecified</pose>
		<truncated>0</truncated>
		<difficult>0</difficult>
		<bndbox>
			<xmin>3567</xmin>
			<ymin>1779</ymin>
			<xmax>3896</xmax>
			<ymax>2148</ymax>
		</bndbox>
	</object>
</annotation>
