<annotation>
	<folder>未处理</folder>
	<filename>IMG_4837.JPG</filename>
	<path>D:\360MoveData\Users\SFJ\Desktop\标注2\未处理\IMG_4837.JPG</path>
	<source>
		<database>Unknown</database>
	</source>
	<size>
		<width>4032</width>
		<height>3024</height>
		<depth>3</depth>
	</size>
	<segmented>0</segmented>
	<object>
		<name>R</name>
		<pose>Unspecified</pose>
		<truncated>0</truncated>
		<difficult>0</difficult>
		<bndbox>
			<xmin>586</xmin>
			<ymin>1503</ymin>
			<xmax>898</xmax>
			<ymax>1811</ymax>
		</bndbox>
	</object>
	<object>
		<name>R</name>
		<pose>Unspecified</pose>
		<truncated>0</truncated>
		<difficult>0</difficult>
		<bndbox>
			<xmin>834</xmin>
			<ymin>1344</ymin>
			<xmax>1016</xmax>
			<ymax>1537</ymax>
		</bndbox>
	</object>
	<object>
		<name>R</name>
		<pose>Unspecified</pose>
		<truncated>0</truncated>
		<difficult>0</difficult>
		<bndbox>
			<xmin>760</xmin>
			<ymin>1273</ymin>
			<xmax>893</xmax>
			<ymax>1420</ymax>
		</bndbox>
	</object>
	<object>
		<name>R</name>
		<pose>Unspecified</pose>
		<truncated>0</truncated>
		<difficult>0</difficult>
		<bndbox>
			<xmin>772</xmin>
			<ymin>1255</ymin>
			<xmax>885</xmax>
			<ymax>1370</ymax>
		</bndbox>
	</object>
	<object>
		<name>R</name>
		<pose>Unspecified</pose>
		<truncated>0</truncated>
		<difficult>0</difficult>
		<bndbox>
			<xmin>862</xmin>
			<ymin>1214</ymin>
			<xmax>964</xmax>
			<ymax>1307</ymax>
		</bndbox>
	</object>
	<object>
		<name>R</name>
		<pose>Unspecified</pose>
		<truncated>0</truncated>
		<difficult>0</difficult>
		<bndbox>
			<xmin>962</xmin>
			<ymin>1187</ymin>
			<xmax>1051</xmax>
			<ymax>1280</ymax>
		</bndbox>
	</object>
	<object>
		<name>R</name>
		<pose>Unspecified</pose>
		<truncated>0</truncated>
		<difficult>0</difficult>
		<bndbox>
			<xmin>1014</xmin>
			<ymin>1177</ymin>
			<xmax>1079</xmax>
			<ymax>1256</ymax>
		</bndbox>
	</object>
	<object>
		<name>R</name>
		<pose>Unspecified</pose>
		<truncated>0</truncated>
		<difficult>0</difficult>
		<bndbox>
			<xmin>1058</xmin>
			<ymin>1156</ymin>
			<xmax>1128</xmax>
			<ymax>1225</ymax>
		</bndbox>
	</object>
	<object>
		<name>B</name>
		<pose>Unspecified</pose>
		<truncated>0</truncated>
		<difficult>0</difficult>
		<bndbox>
			<xmin>1650</xmin>
			<ymin>1144</ymin>
			<xmax>1702</xmax>
			<ymax>1200</ymax>
		</bndbox>
	</object>
	<object>
		<name>B</name>
		<pose>Unspecified</pose>
		<truncated>0</truncated>
		<difficult>0</difficult>
		<bndbox>
			<xmin>1744</xmin>
			<ymin>1141</ymin>
			<xmax>1802</xmax>
			<ymax>1207</ymax>
		</bndbox>
	</object>
	<object>
		<name>B</name>
		<pose>Unspecified</pose>
		<truncated>0</truncated>
		<difficult>0</difficult>
		<bndbox>
			<xmin>1795</xmin>
			<ymin>1149</ymin>
			<xmax>1870</xmax>
			<ymax>1229</ymax>
		</bndbox>
	</object>
	<object>
		<name>B</name>
		<pose>Unspecified</pose>
		<truncated>0</truncated>
		<difficult>0</difficult>
		<bndbox>
			<xmin>1918</xmin>
			<ymin>1165</ymin>
			<xmax>1986</xmax>
			<ymax>1251</ymax>
		</bndbox>
	</object>
	<object>
		<name>B</name>
		<pose>Unspecified</pose>
		<truncated>0</truncated>
		<difficult>0</difficult>
		<bndbox>
			<xmin>2034</xmin>
			<ymin>1197</ymin>
			<xmax>2128</xmax>
			<ymax>1301</ymax>
		</bndbox>
	</object>
	<object>
		<name>B</name>
		<pose>Unspecified</pose>
		<truncated>0</truncated>
		<difficult>0</difficult>
		<bndbox>
			<xmin>2334</xmin>
			<ymin>1233</ymin>
			<xmax>2462</xmax>
			<ymax>1367</ymax>
		</bndbox>
	</object>
	<object>
		<name>B</name>
		<pose>Unspecified</pose>
		<truncated>0</truncated>
		<difficult>0</difficult>
		<bndbox>
			<xmin>2556</xmin>
			<ymin>1271</ymin>
			<xmax>2708</xmax>
			<ymax>1437</ymax>
		</bndbox>
	</object>
	<object>
		<name>B</name>
		<pose>Unspecified</pose>
		<truncated>0</truncated>
		<difficult>0</difficult>
		<bndbox>
			<xmin>3420</xmin>
			<ymin>1383</ymin>
			<xmax>3694</xmax>
			<ymax>1649</ymax>
		</bndbox>
	</object>
</annotation>
