<annotation>
	<folder>待处理图片</folder>
	<filename>IMG_5129.JPG</filename>
	<path>C:\Users\Lenovo\Desktop\待处理图片\IMG_5129.JPG</path>
	<source>
		<database>Unknown</database>
	</source>
	<size>
		<width>4032</width>
		<height>3024</height>
		<depth>3</depth>
	</size>
	<segmented>0</segmented>
	<object>
		<name>B</name>
		<pose>Unspecified</pose>
		<truncated>0</truncated>
		<difficult>0</difficult>
		<bndbox>
			<xmin>524</xmin>
			<ymin>1369</ymin>
			<xmax>717</xmax>
			<ymax>1582</ymax>
		</bndbox>
	</object>
	<object>
		<name>B</name>
		<pose>Unspecified</pose>
		<truncated>0</truncated>
		<difficult>0</difficult>
		<bndbox>
			<xmin>1069</xmin>
			<ymin>1224</ymin>
			<xmax>1217</xmax>
			<ymax>1395</ymax>
		</bndbox>
	</object>
	<object>
		<name>B</name>
		<pose>Unspecified</pose>
		<truncated>0</truncated>
		<difficult>0</difficult>
		<bndbox>
			<xmin>1491</xmin>
			<ymin>1095</ymin>
			<xmax>1604</xmax>
			<ymax>1224</ymax>
		</bndbox>
	</object>
	<object>
		<name>B</name>
		<pose>Unspecified</pose>
		<truncated>0</truncated>
		<difficult>0</difficult>
		<bndbox>
			<xmin>1940</xmin>
			<ymin>996</ymin>
			<xmax>2017</xmax>
			<ymax>1086</ymax>
		</bndbox>
	</object>
	<object>
		<name>R</name>
		<pose>Unspecified</pose>
		<truncated>0</truncated>
		<difficult>0</difficult>
		<bndbox>
			<xmin>2881</xmin>
			<ymin>976</ymin>
			<xmax>2968</xmax>
			<ymax>1076</ymax>
		</bndbox>
	</object>
	<object>
		<name>R</name>
		<pose>Unspecified</pose>
		<truncated>0</truncated>
		<difficult>0</difficult>
		<bndbox>
			<xmin>2722</xmin>
			<ymin>1083</ymin>
			<xmax>2851</xmax>
			<ymax>1212</ymax>
		</bndbox>
	</object>
	<object>
		<name>R</name>
		<pose>Unspecified</pose>
		<truncated>0</truncated>
		<difficult>0</difficult>
		<bndbox>
			<xmin>2820</xmin>
			<ymin>1319</ymin>
			<xmax>3012</xmax>
			<ymax>1542</ymax>
		</bndbox>
	</object>
	<object>
		<name>R</name>
		<pose>Unspecified</pose>
		<truncated>0</truncated>
		<difficult>0</difficult>
		<bndbox>
			<xmin>2927</xmin>
			<ymin>1430</ymin>
			<xmax>3133</xmax>
			<ymax>1696</ymax>
		</bndbox>
	</object>
	<object>
		<name>R</name>
		<pose>Unspecified</pose>
		<truncated>0</truncated>
		<difficult>0</difficult>
		<bndbox>
			<xmin>3140</xmin>
			<ymin>1784</ymin>
			<xmax>3474</xmax>
			<ymax>2210</ymax>
		</bndbox>
	</object>
</annotation>
