<annotation>
	<folder>xml</folder>
	<filename>IMG_20210429_102922.jpg</filename>
	<path>/home/gu/桌面/标注/顾竣文/xml/IMG_20210429_102922.jpg</path>
	<source>
		<database>Unknown</database>
	</source>
	<size>
		<width>4000</width>
		<height>3000</height>
		<depth>3</depth>
	</size>
	<segmented>0</segmented>
	<object>
		<name>B</name>
		<pose>Unspecified</pose>
		<truncated>0</truncated>
		<difficult>0</difficult>
		<bndbox>
			<xmin>337</xmin>
			<ymin>1321</ymin>
			<xmax>633</xmax>
			<ymax>1677</ymax>
		</bndbox>
	</object>
	<object>
		<name>B</name>
		<pose>Unspecified</pose>
		<truncated>0</truncated>
		<difficult>0</difficult>
		<bndbox>
			<xmin>625</xmin>
			<ymin>963</ymin>
			<xmax>843</xmax>
			<ymax>1183</ymax>
		</bndbox>
	</object>
	<object>
		<name>B</name>
		<pose>Unspecified</pose>
		<truncated>0</truncated>
		<difficult>0</difficult>
		<bndbox>
			<xmin>1403</xmin>
			<ymin>828</ymin>
			<xmax>1531</xmax>
			<ymax>973</ymax>
		</bndbox>
	</object>
	<object>
		<name>B</name>
		<pose>Unspecified</pose>
		<truncated>0</truncated>
		<difficult>0</difficult>
		<bndbox>
			<xmin>1758</xmin>
			<ymin>764</ymin>
			<xmax>1853</xmax>
			<ymax>877</ymax>
		</bndbox>
	</object>
	<object>
		<name>R</name>
		<pose>Unspecified</pose>
		<truncated>0</truncated>
		<difficult>0</difficult>
		<bndbox>
			<xmin>2685</xmin>
			<ymin>911</ymin>
			<xmax>2779</xmax>
			<ymax>1039</ymax>
		</bndbox>
	</object>
	<object>
		<name>R</name>
		<pose>Unspecified</pose>
		<truncated>0</truncated>
		<difficult>0</difficult>
		<bndbox>
			<xmin>2543</xmin>
			<ymin>943</ymin>
			<xmax>2665</xmax>
			<ymax>1079</ymax>
		</bndbox>
	</object>
	<object>
		<name>R</name>
		<pose>Unspecified</pose>
		<truncated>0</truncated>
		<difficult>0</difficult>
		<bndbox>
			<xmin>2487</xmin>
			<ymin>1073</ymin>
			<xmax>2625</xmax>
			<ymax>1257</ymax>
		</bndbox>
	</object>
	<object>
		<name>R</name>
		<pose>Unspecified</pose>
		<truncated>0</truncated>
		<difficult>0</difficult>
		<bndbox>
			<xmin>2523</xmin>
			<ymin>1341</ymin>
			<xmax>2763</xmax>
			<ymax>1611</ymax>
		</bndbox>
	</object>
</annotation>
