<annotation>
	<folder>待处理图片</folder>
	<filename>IMG_5061.JPG</filename>
	<path>C:\Users\Lenovo\Desktop\待处理图片\IMG_5061.JPG</path>
	<source>
		<database>Unknown</database>
	</source>
	<size>
		<width>4032</width>
		<height>3024</height>
		<depth>3</depth>
	</size>
	<segmented>0</segmented>
	<object>
		<name>B</name>
		<pose>Unspecified</pose>
		<truncated>0</truncated>
		<difficult>0</difficult>
		<bndbox>
			<xmin>524</xmin>
			<ymin>1726</ymin>
			<xmax>810</xmax>
			<ymax>2060</ymax>
		</bndbox>
	</object>
	<object>
		<name>B</name>
		<pose>Unspecified</pose>
		<truncated>0</truncated>
		<difficult>0</difficult>
		<bndbox>
			<xmin>1658</xmin>
			<ymin>1332</ymin>
			<xmax>1793</xmax>
			<ymax>1508</ymax>
		</bndbox>
	</object>
	<object>
		<name>B</name>
		<pose>Unspecified</pose>
		<truncated>0</truncated>
		<difficult>0</difficult>
		<bndbox>
			<xmin>1999</xmin>
			<ymin>1169</ymin>
			<xmax>2094</xmax>
			<ymax>1295</ymax>
		</bndbox>
	</object>
	<object>
		<name>B</name>
		<pose>Unspecified</pose>
		<truncated>0</truncated>
		<difficult>0</difficult>
		<bndbox>
			<xmin>2156</xmin>
			<ymin>1114</ymin>
			<xmax>2240</xmax>
			<ymax>1221</ymax>
		</bndbox>
	</object>
	<object>
		<name>B</name>
		<pose>Unspecified</pose>
		<truncated>0</truncated>
		<difficult>0</difficult>
		<bndbox>
			<xmin>2266</xmin>
			<ymin>1054</ymin>
			<xmax>2343</xmax>
			<ymax>1141</ymax>
		</bndbox>
	</object>
	<object>
		<name>B</name>
		<pose>Unspecified</pose>
		<truncated>0</truncated>
		<difficult>0</difficult>
		<bndbox>
			<xmin>2487</xmin>
			<ymin>991</ymin>
			<xmax>2546</xmax>
			<ymax>1065</ymax>
		</bndbox>
	</object>
	<object>
		<name>R</name>
		<pose>Unspecified</pose>
		<truncated>0</truncated>
		<difficult>0</difficult>
		<bndbox>
			<xmin>3266</xmin>
			<ymin>965</ymin>
			<xmax>3331</xmax>
			<ymax>1044</ymax>
		</bndbox>
	</object>
	<object>
		<name>R</name>
		<pose>Unspecified</pose>
		<truncated>0</truncated>
		<difficult>0</difficult>
		<bndbox>
			<xmin>3214</xmin>
			<ymin>1024</ymin>
			<xmax>3309</xmax>
			<ymax>1117</ymax>
		</bndbox>
	</object>
	<object>
		<name>R</name>
		<pose>Unspecified</pose>
		<truncated>0</truncated>
		<difficult>0</difficult>
		<bndbox>
			<xmin>3423</xmin>
			<ymin>1113</ymin>
			<xmax>3564</xmax>
			<ymax>1247</ymax>
		</bndbox>
	</object>
	<object>
		<name>R</name>
		<pose>Unspecified</pose>
		<truncated>0</truncated>
		<difficult>0</difficult>
		<bndbox>
			<xmin>3530</xmin>
			<ymin>1146</ymin>
			<xmax>3664</xmax>
			<ymax>1293</ymax>
		</bndbox>
	</object>
	<object>
		<name>R</name>
		<pose>Unspecified</pose>
		<truncated>0</truncated>
		<difficult>0</difficult>
		<bndbox>
			<xmin>3750</xmin>
			<ymin>1226</ymin>
			<xmax>3910</xmax>
			<ymax>1407</ymax>
		</bndbox>
	</object>
</annotation>
