<annotation>
	<folder>zhaopian3</folder>
	<filename>IMG_4797.JPG</filename>
	<path>C:\Users\86198\Desktop\zhaopian3\IMG_4797.JPG</path>
	<source>
		<database>Unknown</database>
	</source>
	<size>
		<width>4032</width>
		<height>3024</height>
		<depth>3</depth>
	</size>
	<segmented>0</segmented>
	<object>
		<name>R</name>
		<pose>Unspecified</pose>
		<truncated>0</truncated>
		<difficult>0</difficult>
		<bndbox>
			<xmin>2763</xmin>
			<ymin>1305</ymin>
			<xmax>2835</xmax>
			<ymax>1373</ymax>
		</bndbox>
	</object>
	<object>
		<name>R</name>
		<pose>Unspecified</pose>
		<truncated>0</truncated>
		<difficult>0</difficult>
		<bndbox>
			<xmin>2673</xmin>
			<ymin>1328</ymin>
			<xmax>2746</xmax>
			<ymax>1402</ymax>
		</bndbox>
	</object>
	<object>
		<name>R</name>
		<pose>Unspecified</pose>
		<truncated>0</truncated>
		<difficult>0</difficult>
		<bndbox>
			<xmin>2568</xmin>
			<ymin>1351</ymin>
			<xmax>2648</xmax>
			<ymax>1446</ymax>
		</bndbox>
	</object>
	<object>
		<name>R</name>
		<pose>Unspecified</pose>
		<truncated>0</truncated>
		<difficult>0</difficult>
		<bndbox>
			<xmin>2374</xmin>
			<ymin>1395</ymin>
			<xmax>2487</xmax>
			<ymax>1523</ymax>
		</bndbox>
	</object>
	<object>
		<name>R</name>
		<pose>Unspecified</pose>
		<truncated>0</truncated>
		<difficult>0</difficult>
		<bndbox>
			<xmin>2548</xmin>
			<ymin>1456</ymin>
			<xmax>2690</xmax>
			<ymax>1630</ymax>
		</bndbox>
	</object>
	<object>
		<name>R</name>
		<pose>Unspecified</pose>
		<truncated>0</truncated>
		<difficult>0</difficult>
		<bndbox>
			<xmin>2762</xmin>
			<ymin>1531</ymin>
			<xmax>2987</xmax>
			<ymax>1788</ymax>
		</bndbox>
	</object>
	<object>
		<name>R</name>
		<pose>Unspecified</pose>
		<truncated>0</truncated>
		<difficult>0</difficult>
		<bndbox>
			<xmin>1643</xmin>
			<ymin>1531</ymin>
			<xmax>1825</xmax>
			<ymax>1756</ymax>
		</bndbox>
	</object>
	<object>
		<name>R</name>
		<pose>Unspecified</pose>
		<truncated>0</truncated>
		<difficult>0</difficult>
		<bndbox>
			<xmin>1445</xmin>
			<ymin>1904</ymin>
			<xmax>1916</xmax>
			<ymax>2464</ymax>
		</bndbox>
	</object>
	<object>
		<name>B</name>
		<pose>Unspecified</pose>
		<truncated>0</truncated>
		<difficult>0</difficult>
		<bndbox>
			<xmin>1677</xmin>
			<ymin>1695</ymin>
			<xmax>1950</xmax>
			<ymax>2094</ymax>
		</bndbox>
	</object>
	<object>
		<name>B</name>
		<pose>Unspecified</pose>
		<truncated>0</truncated>
		<difficult>0</difficult>
		<bndbox>
			<xmin>1590</xmin>
			<ymin>1454</ymin>
			<xmax>1732</xmax>
			<ymax>1628</ymax>
		</bndbox>
	</object>
	<object>
		<name>B</name>
		<pose>Unspecified</pose>
		<truncated>0</truncated>
		<difficult>0</difficult>
		<bndbox>
			<xmin>1694</xmin>
			<ymin>1384</ymin>
			<xmax>1811</xmax>
			<ymax>1507</ymax>
		</bndbox>
	</object>
	<object>
		<name>B</name>
		<pose>Unspecified</pose>
		<truncated>0</truncated>
		<difficult>0</difficult>
		<bndbox>
			<xmin>1869</xmin>
			<ymin>1362</ymin>
			<xmax>1961</xmax>
			<ymax>1464</ymax>
		</bndbox>
	</object>
	<object>
		<name>B</name>
		<pose>Unspecified</pose>
		<truncated>0</truncated>
		<difficult>0</difficult>
		<bndbox>
			<xmin>2211</xmin>
			<ymin>1359</ymin>
			<xmax>2310</xmax>
			<ymax>1460</ymax>
		</bndbox>
	</object>
	<object>
		<name>B</name>
		<pose>Unspecified</pose>
		<truncated>0</truncated>
		<difficult>0</difficult>
		<bndbox>
			<xmin>240</xmin>
			<ymin>1485</ymin>
			<xmax>410</xmax>
			<ymax>1694</ymax>
		</bndbox>
	</object>
	<object>
		<name>B</name>
		<pose>Unspecified</pose>
		<truncated>0</truncated>
		<difficult>0</difficult>
		<bndbox>
			<xmin>115</xmin>
			<ymin>1597</ymin>
			<xmax>406</xmax>
			<ymax>1892</ymax>
		</bndbox>
	</object>
	<object>
		<name>B</name>
		<pose>Unspecified</pose>
		<truncated>1</truncated>
		<difficult>0</difficult>
		<bndbox>
			<xmin>1</xmin>
			<ymin>2047</ymin>
			<xmax>352</xmax>
			<ymax>2760</ymax>
		</bndbox>
	</object>
</annotation>
