<annotation>
	<folder>JPE</folder>
	<filename>00110.jpg</filename>
	<path>F:\JPE\00110.jpg</path>
	<source>
		<database>Unknown</database>
	</source>
	<size>
		<width>4096</width>
		<height>3072</height>
		<depth>3</depth>
	</size>
	<segmented>0</segmented>
	<object>
		<name>red-cone</name>
		<pose>Unspecified</pose>
		<truncated>0</truncated>
		<difficult>0</difficult>
		<bndbox>
			<xmin>677</xmin>
			<ymin>1596</ymin>
			<xmax>886</xmax>
			<ymax>1868</ymax>
		</bndbox>
	</object>
	<object>
		<name>red-cone</name>
		<pose>Unspecified</pose>
		<truncated>0</truncated>
		<difficult>0</difficult>
		<bndbox>
			<xmin>1247</xmin>
			<ymin>1208</ymin>
			<xmax>1348</xmax>
			<ymax>1337</ymax>
		</bndbox>
	</object>
	<object>
		<name>red-cone</name>
		<pose>Unspecified</pose>
		<truncated>0</truncated>
		<difficult>0</difficult>
		<bndbox>
			<xmin>1147</xmin>
			<ymin>1095</ymin>
			<xmax>1220</xmax>
			<ymax>1178</ymax>
		</bndbox>
	</object>
	<object>
		<name>yellow-cone</name>
		<pose>Unspecified</pose>
		<truncated>0</truncated>
		<difficult>0</difficult>
		<bndbox>
			<xmin>1033</xmin>
			<ymin>1068</ymin>
			<xmax>1088</xmax>
			<ymax>1135</ymax>
		</bndbox>
	</object>
	<object>
		<name>yellow-cone</name>
		<pose>Unspecified</pose>
		<truncated>0</truncated>
		<difficult>0</difficult>
		<bndbox>
			<xmin>1797</xmin>
			<ymin>1012</ymin>
			<xmax>1852</xmax>
			<ymax>1071</ymax>
		</bndbox>
	</object>
	<object>
		<name>blue-cone</name>
		<pose>Unspecified</pose>
		<truncated>0</truncated>
		<difficult>0</difficult>
		<bndbox>
			<xmin>2184</xmin>
			<ymin>1043</ymin>
			<xmax>2239</xmax>
			<ymax>1119</ymax>
		</bndbox>
	</object>
	<object>
		<name>blue-cone</name>
		<pose>Unspecified</pose>
		<truncated>0</truncated>
		<difficult>0</difficult>
		<bndbox>
			<xmin>2622</xmin>
			<ymin>1129</ymin>
			<xmax>2722</xmax>
			<ymax>1249</ymax>
		</bndbox>
	</object>
	<object>
		<name>blue-cone</name>
		<pose>Unspecified</pose>
		<truncated>0</truncated>
		<difficult>0</difficult>
		<bndbox>
			<xmin>3276</xmin>
			<ymin>1467</ymin>
			<xmax>3528</xmax>
			<ymax>1731</ymax>
		</bndbox>
	</object>
</annotation>
