<annotation>
	<folder>JPE</folder>
	<filename>00187.jpg</filename>
	<path>F:\JPE\00187.jpg</path>
	<source>
		<database>Unknown</database>
	</source>
	<size>
		<width>4096</width>
		<height>3072</height>
		<depth>3</depth>
	</size>
	<segmented>0</segmented>
	<object>
		<name>blue-cone</name>
		<pose>Unspecified</pose>
		<truncated>0</truncated>
		<difficult>0</difficult>
		<bndbox>
			<xmin>937</xmin>
			<ymin>1888</ymin>
			<xmax>1169</xmax>
			<ymax>2151</ymax>
		</bndbox>
	</object>
	<object>
		<name>blue-cone</name>
		<pose>Unspecified</pose>
		<truncated>0</truncated>
		<difficult>0</difficult>
		<bndbox>
			<xmin>1384</xmin>
			<ymin>1750</ymin>
			<xmax>1526</xmax>
			<ymax>1903</ymax>
		</bndbox>
	</object>
	<object>
		<name>yellow-cone</name>
		<pose>Unspecified</pose>
		<truncated>0</truncated>
		<difficult>0</difficult>
		<bndbox>
			<xmin>1557</xmin>
			<ymin>1670</ymin>
			<xmax>1625</xmax>
			<ymax>1752</ymax>
		</bndbox>
	</object>
	<object>
		<name>yellow-cone</name>
		<pose>Unspecified</pose>
		<truncated>0</truncated>
		<difficult>0</difficult>
		<bndbox>
			<xmin>2255</xmin>
			<ymin>1666</ymin>
			<xmax>2316</xmax>
			<ymax>1747</ymax>
		</bndbox>
	</object>
	<object>
		<name>red-cone</name>
		<pose>Unspecified</pose>
		<truncated>0</truncated>
		<difficult>0</difficult>
		<bndbox>
			<xmin>2352</xmin>
			<ymin>1689</ymin>
			<xmax>2434</xmax>
			<ymax>1796</ymax>
		</bndbox>
	</object>
	<object>
		<name>red-cone</name>
		<pose>Unspecified</pose>
		<truncated>0</truncated>
		<difficult>0</difficult>
		<bndbox>
			<xmin>2507</xmin>
			<ymin>1756</ymin>
			<xmax>2623</xmax>
			<ymax>1908</ymax>
		</bndbox>
	</object>
	<object>
		<name>red-cone</name>
		<pose>Unspecified</pose>
		<truncated>0</truncated>
		<difficult>0</difficult>
		<bndbox>
			<xmin>2966</xmin>
			<ymin>1906</ymin>
			<xmax>3223</xmax>
			<ymax>2185</ymax>
		</bndbox>
	</object>
</annotation>
