<annotation>
	<folder>photo</folder>
	<filename>00548.jpg</filename>
	<path>C:\Users\cx\Desktop\photo_rename\photo\00548.jpg</path>
	<source>
		<database>Unknown</database>
	</source>
	<size>
		<width>3072</width>
		<height>4096</height>
		<depth>3</depth>
	</size>
	<segmented>0</segmented>
	<object>
		<name>red-cone</name>
		<pose>Unspecified</pose>
		<truncated>0</truncated>
		<difficult>0</difficult>
		<bndbox>
			<xmin>127</xmin>
			<ymin>1957</ymin>
			<xmax>373</xmax>
			<ymax>2220</ymax>
		</bndbox>
	</object>
	<object>
		<name>red-cone</name>
		<pose>Unspecified</pose>
		<truncated>0</truncated>
		<difficult>0</difficult>
		<bndbox>
			<xmin>812</xmin>
			<ymin>1787</ymin>
			<xmax>948</xmax>
			<ymax>1928</ymax>
		</bndbox>
	</object>
	<object>
		<name>red-cone</name>
		<pose>Unspecified</pose>
		<truncated>0</truncated>
		<difficult>0</difficult>
		<bndbox>
			<xmin>1024</xmin>
			<ymin>1723</ymin>
			<xmax>1108</xmax>
			<ymax>1819</ymax>
		</bndbox>
	</object>
	<object>
		<name>yellow-cone</name>
		<pose>Unspecified</pose>
		<truncated>0</truncated>
		<difficult>0</difficult>
		<bndbox>
			<xmin>1141</xmin>
			<ymin>1690</ymin>
			<xmax>1207</xmax>
			<ymax>1761</ymax>
		</bndbox>
	</object>
	<object>
		<name>yellow-cone</name>
		<pose>Unspecified</pose>
		<truncated>0</truncated>
		<difficult>0</difficult>
		<bndbox>
			<xmin>1743</xmin>
			<ymin>1694</ymin>
			<xmax>1798</xmax>
			<ymax>1767</ymax>
		</bndbox>
	</object>
	<object>
		<name>blue-cone</name>
		<pose>Unspecified</pose>
		<truncated>0</truncated>
		<difficult>0</difficult>
		<bndbox>
			<xmin>1825</xmin>
			<ymin>1721</ymin>
			<xmax>1915</xmax>
			<ymax>1820</ymax>
		</bndbox>
	</object>
	<object>
		<name>blue-cone</name>
		<pose>Unspecified</pose>
		<truncated>0</truncated>
		<difficult>0</difficult>
		<bndbox>
			<xmin>2115</xmin>
			<ymin>1788</ymin>
			<xmax>2251</xmax>
			<ymax>1941</ymax>
		</bndbox>
	</object>
	<object>
		<name>blue-cone</name>
		<pose>Unspecified</pose>
		<truncated>0</truncated>
		<difficult>0</difficult>
		<bndbox>
			<xmin>2620</xmin>
			<ymin>1974</ymin>
			<xmax>2883</xmax>
			<ymax>2254</ymax>
		</bndbox>
	</object>
</annotation>
