<annotation>
	<folder>photo</folder>
	<filename>00587.jpg</filename>
	<path>C:\Users\cx\Desktop\photo_rename\photo\00587.jpg</path>
	<source>
		<database>Unknown</database>
	</source>
	<size>
		<width>3072</width>
		<height>4096</height>
		<depth>3</depth>
	</size>
	<segmented>0</segmented>
	<object>
		<name>blue-cone</name>
		<pose>Unspecified</pose>
		<truncated>0</truncated>
		<difficult>0</difficult>
		<bndbox>
			<xmin>131</xmin>
			<ymin>1999</ymin>
			<xmax>369</xmax>
			<ymax>2261</ymax>
		</bndbox>
	</object>
	<object>
		<name>blue-cone</name>
		<pose>Unspecified</pose>
		<truncated>0</truncated>
		<difficult>0</difficult>
		<bndbox>
			<xmin>704</xmin>
			<ymin>1726</ymin>
			<xmax>822</xmax>
			<ymax>1869</ymax>
		</bndbox>
	</object>
	<object>
		<name>blue-cone</name>
		<pose>Unspecified</pose>
		<truncated>0</truncated>
		<difficult>0</difficult>
		<bndbox>
			<xmin>983</xmin>
			<ymin>1609</ymin>
			<xmax>1066</xmax>
			<ymax>1708</ymax>
		</bndbox>
	</object>
	<object>
		<name>yellow-cone</name>
		<pose>Unspecified</pose>
		<truncated>0</truncated>
		<difficult>0</difficult>
		<bndbox>
			<xmin>1073</xmin>
			<ymin>1559</ymin>
			<xmax>1144</xmax>
			<ymax>1637</ymax>
		</bndbox>
	</object>
	<object>
		<name>yellow-cone</name>
		<pose>Unspecified</pose>
		<truncated>0</truncated>
		<difficult>0</difficult>
		<bndbox>
			<xmin>1896</xmin>
			<ymin>1562</ymin>
			<xmax>1959</xmax>
			<ymax>1640</ymax>
		</bndbox>
	</object>
	<object>
		<name>red-cone</name>
		<pose>Unspecified</pose>
		<truncated>0</truncated>
		<difficult>0</difficult>
		<bndbox>
			<xmin>2030</xmin>
			<ymin>1621</ymin>
			<xmax>2110</xmax>
			<ymax>1716</ymax>
		</bndbox>
	</object>
	<object>
		<name>red-cone</name>
		<pose>Unspecified</pose>
		<truncated>0</truncated>
		<difficult>0</difficult>
		<bndbox>
			<xmin>2230</xmin>
			<ymin>1748</ymin>
			<xmax>2351</xmax>
			<ymax>1893</ymax>
		</bndbox>
	</object>
	<object>
		<name>red-cone</name>
		<pose>Unspecified</pose>
		<truncated>0</truncated>
		<difficult>0</difficult>
		<bndbox>
			<xmin>2745</xmin>
			<ymin>2006</ymin>
			<xmax>2980</xmax>
			<ymax>2256</ymax>
		</bndbox>
	</object>
</annotation>
