<annotation>
	<folder>photo</folder>
	<filename>00590.jpg</filename>
	<path>C:\Users\cx\Desktop\photo_rename\photo\00590.jpg</path>
	<source>
		<database>Unknown</database>
	</source>
	<size>
		<width>3072</width>
		<height>4096</height>
		<depth>3</depth>
	</size>
	<segmented>0</segmented>
	<object>
		<name>red-cone</name>
		<pose>Unspecified</pose>
		<truncated>0</truncated>
		<difficult>0</difficult>
		<bndbox>
			<xmin>2783</xmin>
			<ymin>2012</ymin>
			<xmax>3013</xmax>
			<ymax>2264</ymax>
		</bndbox>
	</object>
	<object>
		<name>red-cone</name>
		<pose>Unspecified</pose>
		<truncated>0</truncated>
		<difficult>0</difficult>
		<bndbox>
			<xmin>2262</xmin>
			<ymin>1751</ymin>
			<xmax>2379</xmax>
			<ymax>1895</ymax>
		</bndbox>
	</object>
	<object>
		<name>red-cone</name>
		<pose>Unspecified</pose>
		<truncated>0</truncated>
		<difficult>0</difficult>
		<bndbox>
			<xmin>2059</xmin>
			<ymin>1624</ymin>
			<xmax>2140</xmax>
			<ymax>1717</ymax>
		</bndbox>
	</object>
	<object>
		<name>yellow-cone</name>
		<pose>Unspecified</pose>
		<truncated>0</truncated>
		<difficult>0</difficult>
		<bndbox>
			<xmin>1923</xmin>
			<ymin>1565</ymin>
			<xmax>1987</xmax>
			<ymax>1641</ymax>
		</bndbox>
	</object>
	<object>
		<name>yellow-cone</name>
		<pose>Unspecified</pose>
		<truncated>0</truncated>
		<difficult>0</difficult>
		<bndbox>
			<xmin>1101</xmin>
			<ymin>1559</ymin>
			<xmax>1172</xmax>
			<ymax>1634</ymax>
		</bndbox>
	</object>
	<object>
		<name>blue-cone</name>
		<pose>Unspecified</pose>
		<truncated>0</truncated>
		<difficult>0</difficult>
		<bndbox>
			<xmin>1012</xmin>
			<ymin>1609</ymin>
			<xmax>1093</xmax>
			<ymax>1705</ymax>
		</bndbox>
	</object>
	<object>
		<name>blue-cone</name>
		<pose>Unspecified</pose>
		<truncated>0</truncated>
		<difficult>0</difficult>
		<bndbox>
			<xmin>730</xmin>
			<ymin>1722</ymin>
			<xmax>848</xmax>
			<ymax>1866</ymax>
		</bndbox>
	</object>
	<object>
		<name>blue-cone</name>
		<pose>Unspecified</pose>
		<truncated>0</truncated>
		<difficult>0</difficult>
		<bndbox>
			<xmin>157</xmin>
			<ymin>1993</ymin>
			<xmax>397</xmax>
			<ymax>2253</ymax>
		</bndbox>
	</object>
</annotation>
