<annotation>
	<folder>photo</folder>
	<filename>00644.jpg</filename>
	<path>C:\Users\cx\Desktop\photo_rename\photo\00644.jpg</path>
	<source>
		<database>Unknown</database>
	</source>
	<size>
		<width>3072</width>
		<height>4096</height>
		<depth>3</depth>
	</size>
	<segmented>0</segmented>
	<object>
		<name>red-cone</name>
		<pose>Unspecified</pose>
		<truncated>0</truncated>
		<difficult>0</difficult>
		<bndbox>
			<xmin>64</xmin>
			<ymin>1407</ymin>
			<xmax>302</xmax>
			<ymax>1669</ymax>
		</bndbox>
	</object>
	<object>
		<name>red-cone</name>
		<pose>Unspecified</pose>
		<truncated>0</truncated>
		<difficult>0</difficult>
		<bndbox>
			<xmin>774</xmin>
			<ymin>1107</ymin>
			<xmax>906</xmax>
			<ymax>1252</ymax>
		</bndbox>
	</object>
	<object>
		<name>red-cone</name>
		<pose>Unspecified</pose>
		<truncated>0</truncated>
		<difficult>0</difficult>
		<bndbox>
			<xmin>977</xmin>
			<ymin>995</ymin>
			<xmax>1058</xmax>
			<ymax>1101</ymax>
		</bndbox>
	</object>
	<object>
		<name>yellow-cone</name>
		<pose>Unspecified</pose>
		<truncated>0</truncated>
		<difficult>0</difficult>
		<bndbox>
			<xmin>1102</xmin>
			<ymin>925</ymin>
			<xmax>1166</xmax>
			<ymax>1005</ymax>
		</bndbox>
	</object>
	<object>
		<name>yellow-cone</name>
		<pose>Unspecified</pose>
		<truncated>0</truncated>
		<difficult>0</difficult>
		<bndbox>
			<xmin>1972</xmin>
			<ymin>957</ymin>
			<xmax>2032</xmax>
			<ymax>1037</ymax>
		</bndbox>
	</object>
	<object>
		<name>blue-cone</name>
		<pose>Unspecified</pose>
		<truncated>0</truncated>
		<difficult>0</difficult>
		<bndbox>
			<xmin>2058</xmin>
			<ymin>1025</ymin>
			<xmax>2147</xmax>
			<ymax>1133</ymax>
		</bndbox>
	</object>
	<object>
		<name>blue-cone</name>
		<pose>Unspecified</pose>
		<truncated>0</truncated>
		<difficult>0</difficult>
		<bndbox>
			<xmin>2287</xmin>
			<ymin>1148</ymin>
			<xmax>2417</xmax>
			<ymax>1297</ymax>
		</bndbox>
	</object>
	<object>
		<name>blue-cone</name>
		<pose>Unspecified</pose>
		<truncated>0</truncated>
		<difficult>0</difficult>
		<bndbox>
			<xmin>2828</xmin>
			<ymin>1501</ymin>
			<xmax>3058</xmax>
			<ymax>1774</ymax>
		</bndbox>
	</object>
</annotation>
