<annotation>
	<folder>史佳伟</folder>
	<filename>001217.jpg</filename>
	<path>C:\Users\shijiawei\Desktop\yoloimg\史佳伟\001217.jpg</path>
	<source>
		<database>Unknown</database>
	</source>
	<size>
		<width>1600</width>
		<height>1200</height>
		<depth>3</depth>
	</size>
	<segmented>0</segmented>
	<object>
		<name>red</name>
		<pose>Unspecified</pose>
		<truncated>0</truncated>
		<difficult>0</difficult>
		<bndbox>
			<xmin>247</xmin>
			<ymin>284</ymin>
			<xmax>457</xmax>
			<ymax>558</ymax>
		</bndbox>
	</object>
</annotation>
