<annotation>
	<folder>蒋一铭</folder>
	<filename>001799.jpg</filename>
	<path>C:\Users\DJW\Desktop\xml\蒋一铭\001799.jpg</path>
	<source>
		<database>Unknown</database>
	</source>
	<size>
		<width>1600</width>
		<height>1200</height>
		<depth>3</depth>
	</size>
	<segmented>0</segmented>
	<object>
		<name>blue</name>
		<pose>Unspecified</pose>
		<truncated>0</truncated>
		<difficult>0</difficult>
		<bndbox>
			<xmin>288</xmin>
			<ymin>619</ymin>
			<xmax>356</xmax>
			<ymax>682</ymax>
		</bndbox>
	</object>
	<object>
		<name>blue</name>
		<pose>Unspecified</pose>
		<truncated>0</truncated>
		<difficult>0</difficult>
		<bndbox>
			<xmin>788</xmin>
			<ymin>641</ymin>
			<xmax>862</xmax>
			<ymax>724</ymax>
		</bndbox>
	</object>
</annotation>
