<annotation>
	<folder>yoloimg</folder>
	<filename>470.jpg</filename>
	<path>C:\Users\DJW\Desktop\yoloorg\yoloimg\470.jpg</path>
	<source>
		<database>Unknown</database>
	</source>
	<size>
		<width>1600</width>
		<height>1200</height>
		<depth>3</depth>
	</size>
	<segmented>0</segmented>
	<object>
		<name>red</name>
		<pose>Unspecified</pose>
		<truncated>0</truncated>
		<difficult>0</difficult>
		<bndbox>
			<xmin>1231</xmin>
			<ymin>401</ymin>
			<xmax>1441</xmax>
			<ymax>627</ymax>
		</bndbox>
	</object>
	<object>
		<name>red</name>
		<pose>Unspecified</pose>
		<truncated>0</truncated>
		<difficult>0</difficult>
		<bndbox>
			<xmin>195</xmin>
			<ymin>102</ymin>
			<xmax>408</xmax>
			<ymax>340</ymax>
		</bndbox>
	</object>
	<object>
		<name>blue</name>
		<pose>Unspecified</pose>
		<truncated>0</truncated>
		<difficult>0</difficult>
		<bndbox>
			<xmin>1147</xmin>
			<ymin>171</ymin>
			<xmax>1274</xmax>
			<ymax>312</ymax>
		</bndbox>
	</object>
	<object>
		<name>yellow</name>
		<pose>Unspecified</pose>
		<truncated>0</truncated>
		<difficult>0</difficult>
		<bndbox>
			<xmin>1210</xmin>
			<ymin>97</ymin>
			<xmax>1290</xmax>
			<ymax>215</ymax>
		</bndbox>
	</object>
	<object>
		<name>red</name>
		<pose>Unspecified</pose>
		<truncated>0</truncated>
		<difficult>0</difficult>
		<bndbox>
			<xmin>1234</xmin>
			<ymin>23</ymin>
			<xmax>1328</xmax>
			<ymax>137</ymax>
		</bndbox>
	</object>
</annotation>
