<annotation>
	<folder>JPEGImages1</folder>
	<filename>797.jpg</filename>
	<path>E:\VOCdevkitzhuit\VOC2007\JPEGImages1\797.jpg</path>
	<source>
		<database>Unknown</database>
	</source>
	<size>
		<width>1600</width>
		<height>1200</height>
		<depth>3</depth>
	</size>
	<segmented>0</segmented>
	<object>
		<name>blue</name>
		<pose>Unspecified</pose>
		<truncated>0</truncated>
		<difficult>0</difficult>
		<bndbox>
			<xmin>394</xmin>
			<ymin>316</ymin>
			<xmax>644</xmax>
			<ymax>609</ymax>
		</bndbox>
	</object>
	<object>
		<name>blue</name>
		<pose>Unspecified</pose>
		<truncated>0</truncated>
		<difficult>0</difficult>
		<bndbox>
			<xmin>234</xmin>
			<ymin>5</ymin>
			<xmax>365</xmax>
			<ymax>71</ymax>
		</bndbox>
	</object>
	<object>
		<name>yellow</name>
		<pose>Unspecified</pose>
		<truncated>0</truncated>
		<difficult>0</difficult>
		<bndbox>
			<xmin>861</xmin>
			<ymin>34</ymin>
			<xmax>991</xmax>
			<ymax>208</ymax>
		</bndbox>
	</object>
	<object>
		<name>red</name>
		<pose>Unspecified</pose>
		<truncated>1</truncated>
		<difficult>0</difficult>
		<bndbox>
			<xmin>1036</xmin>
			<ymin>1</ymin>
			<xmax>1127</xmax>
			<ymax>78</ymax>
		</bndbox>
	</object>
</annotation>
