<annotation>
	<folder>all</folder>
	<filename>002269.jpg</filename>
	<path>C:\Users\tb_pc\Desktop\zuitong\标注图片2\all\002269.jpg</path>
	<source>
		<database>Unknown</database>
	</source>
	<size>
		<width>1920</width>
		<height>1080</height>
		<depth>3</depth>
	</size>
	<segmented>0</segmented>
	<object>
		<name>RedCone</name>
		<pose>Unspecified</pose>
		<truncated>0</truncated>
		<difficult>0</difficult>
		<bndbox>
			<xmin>617</xmin>
			<ymin>174</ymin>
			<xmax>684</xmax>
			<ymax>257</ymax>
		</bndbox>
	</object>
	<object>
		<name>RedCone</name>
		<pose>Unspecified</pose>
		<truncated>0</truncated>
		<difficult>0</difficult>
		<bndbox>
			<xmin>1118</xmin>
			<ymin>121</ymin>
			<xmax>1174</xmax>
			<ymax>188</ymax>
		</bndbox>
	</object>
	<object>
		<name>RedCone</name>
		<pose>Unspecified</pose>
		<truncated>0</truncated>
		<difficult>0</difficult>
		<bndbox>
			<xmin>1330</xmin>
			<ymin>64</ymin>
			<xmax>1368</xmax>
			<ymax>111</ymax>
		</bndbox>
	</object>
	<object>
		<name>RedCone</name>
		<pose>Unspecified</pose>
		<truncated>0</truncated>
		<difficult>0</difficult>
		<bndbox>
			<xmin>1291</xmin>
			<ymin>36</ymin>
			<xmax>1323</xmax>
			<ymax>75</ymax>
		</bndbox>
	</object>
	<object>
		<name>RedCone</name>
		<pose>Unspecified</pose>
		<truncated>0</truncated>
		<difficult>0</difficult>
		<bndbox>
			<xmin>1140</xmin>
			<ymin>19</ymin>
			<xmax>1168</xmax>
			<ymax>53</ymax>
		</bndbox>
	</object>
	<object>
		<name>RedCone</name>
		<pose>Unspecified</pose>
		<truncated>0</truncated>
		<difficult>0</difficult>
		<bndbox>
			<xmin>959</xmin>
			<ymin>11</ymin>
			<xmax>985</xmax>
			<ymax>42</ymax>
		</bndbox>
	</object>
	<object>
		<name>RedCone</name>
		<pose>Unspecified</pose>
		<truncated>0</truncated>
		<difficult>0</difficult>
		<bndbox>
			<xmin>736</xmin>
			<ymin>10</ymin>
			<xmax>757</xmax>
			<ymax>37</ymax>
		</bndbox>
	</object>
	<object>
		<name>RedCone</name>
		<pose>Unspecified</pose>
		<truncated>0</truncated>
		<difficult>0</difficult>
		<bndbox>
			<xmin>512</xmin>
			<ymin>11</ymin>
			<xmax>532</xmax>
			<ymax>38</ymax>
		</bndbox>
	</object>
	<object>
		<name>RedCone</name>
		<pose>Unspecified</pose>
		<truncated>0</truncated>
		<difficult>0</difficult>
		<bndbox>
			<xmin>267</xmin>
			<ymin>14</ymin>
			<xmax>288</xmax>
			<ymax>42</ymax>
		</bndbox>
	</object>
	<object>
		<name>YellowCone</name>
		<pose>Unspecified</pose>
		<truncated>0</truncated>
		<difficult>0</difficult>
		<bndbox>
			<xmin>1772</xmin>
			<ymin>18</ymin>
			<xmax>1808</xmax>
			<ymax>57</ymax>
		</bndbox>
	</object>
	<object>
		<name>YellowCone</name>
		<pose>Unspecified</pose>
		<truncated>1</truncated>
		<difficult>0</difficult>
		<bndbox>
			<xmin>1891</xmin>
			<ymin>1</ymin>
			<xmax>1920</xmax>
			<ymax>32</ymax>
		</bndbox>
	</object>
	<object>
		<name>BlueCone</name>
		<pose>Unspecified</pose>
		<truncated>0</truncated>
		<difficult>0</difficult>
		<bndbox>
			<xmin>1606</xmin>
			<ymin>363</ymin>
			<xmax>1727</xmax>
			<ymax>507</ymax>
		</bndbox>
	</object>
	<object>
		<name>BlueCone</name>
		<pose>Unspecified</pose>
		<truncated>0</truncated>
		<difficult>0</difficult>
		<bndbox>
			<xmin>1819</xmin>
			<ymin>185</ymin>
			<xmax>1872</xmax>
			<ymax>280</ymax>
		</bndbox>
	</object>
	<object>
		<name>BlueCone</name>
		<pose>Unspecified</pose>
		<truncated>0</truncated>
		<difficult>0</difficult>
		<bndbox>
			<xmin>1669</xmin>
			<ymin>28</ymin>
			<xmax>1700</xmax>
			<ymax>72</ymax>
		</bndbox>
	</object>
	<object>
		<name>BlueCone</name>
		<pose>Unspecified</pose>
		<truncated>0</truncated>
		<difficult>0</difficult>
		<bndbox>
			<xmin>1384</xmin>
			<ymin>7</ymin>
			<xmax>1415</xmax>
			<ymax>38</ymax>
		</bndbox>
	</object>
	<object>
		<name>BlueCone</name>
		<pose>Unspecified</pose>
		<truncated>1</truncated>
		<difficult>0</difficult>
		<bndbox>
			<xmin>1118</xmin>
			<ymin>1</ymin>
			<xmax>1139</xmax>
			<ymax>31</ymax>
		</bndbox>
	</object>
	<object>
		<name>BlueCone</name>
		<pose>Unspecified</pose>
		<truncated>1</truncated>
		<difficult>0</difficult>
		<bndbox>
			<xmin>830</xmin>
			<ymin>1</ymin>
			<xmax>850</xmax>
			<ymax>27</ymax>
		</bndbox>
	</object>
	<object>
		<name>BlueCone</name>
		<pose>Unspecified</pose>
		<truncated>1</truncated>
		<difficult>0</difficult>
		<bndbox>
			<xmin>548</xmin>
			<ymin>1</ymin>
			<xmax>571</xmax>
			<ymax>27</ymax>
		</bndbox>
	</object>
	<object>
		<name>BlueCone</name>
		<pose>Unspecified</pose>
		<truncated>1</truncated>
		<difficult>0</difficult>
		<bndbox>
			<xmin>241</xmin>
			<ymin>1</ymin>
			<xmax>261</xmax>
			<ymax>30</ymax>
		</bndbox>
	</object>
	<object>
		<name>BigCone</name>
		<pose>Unspecified</pose>
		<truncated>0</truncated>
		<difficult>0</difficult>
		<bndbox>
			<xmin>1736</xmin>
			<ymin>87</ymin>
			<xmax>1866</xmax>
			<ymax>310</ymax>
		</bndbox>
	</object>
	<object>
		<name>BigCone</name>
		<pose>Unspecified</pose>
		<truncated>1</truncated>
		<difficult>0</difficult>
		<bndbox>
			<xmin>1841</xmin>
			<ymin>65</ymin>
			<xmax>1920</xmax>
			<ymax>259</ymax>
		</bndbox>
	</object>
	<object>
		<name>BigCone</name>
		<pose>Unspecified</pose>
		<truncated>0</truncated>
		<difficult>0</difficult>
		<bndbox>
			<xmin>1166</xmin>
			<ymin>30</ymin>
			<xmax>1263</xmax>
			<ymax>175</ymax>
		</bndbox>
	</object>
	<object>
		<name>BigCone</name>
		<pose>Unspecified</pose>
		<truncated>0</truncated>
		<difficult>0</difficult>
		<bndbox>
			<xmin>1024</xmin>
			<ymin>43</ymin>
			<xmax>1119</xmax>
			<ymax>207</ymax>
		</bndbox>
	</object>
</annotation>
