<annotation>
	<folder>王心亮</folder>
	<filename>MER2-231-41U3C(FDA19080001)_2020-09-26_15_27_01_964-997.jpg</filename>
	<path>G:\BaiduNetdiskDownload\王心亮\MER2-231-41U3C(FDA19080001)_2020-09-26_15_27_01_964-997.jpg</path>
	<source>
		<database>Unknown</database>
	</source>
	<size>
		<width>1920</width>
		<height>1200</height>
		<depth>3</depth>
	</size>
	<segmented>0</segmented>
	<object>
		<name>blue</name>
		<pose>Unspecified</pose>
		<truncated>0</truncated>
		<difficult>0</difficult>
		<bndbox>
			<xmin>876</xmin>
			<ymin>730</ymin>
			<xmax>943</xmax>
			<ymax>805</ymax>
		</bndbox>
	</object>
	<object>
		<name>blue</name>
		<pose>Unspecified</pose>
		<truncated>0</truncated>
		<difficult>0</difficult>
		<bndbox>
			<xmin>535</xmin>
			<ymin>661</ymin>
			<xmax>580</xmax>
			<ymax>711</ymax>
		</bndbox>
	</object>
	<object>
		<name>blue</name>
		<pose>Unspecified</pose>
		<truncated>1</truncated>
		<difficult>0</difficult>
		<bndbox>
			<xmin>1</xmin>
			<ymin>636</ymin>
			<xmax>21</xmax>
			<ymax>676</ymax>
		</bndbox>
	</object>
	<object>
		<name>red</name>
		<pose>Unspecified</pose>
		<truncated>0</truncated>
		<difficult>0</difficult>
		<bndbox>
			<xmin>121</xmin>
			<ymin>821</ymin>
			<xmax>209</xmax>
			<ymax>933</ymax>
		</bndbox>
	</object>
	<object>
		<name>red</name>
		<pose>Unspecified</pose>
		<truncated>0</truncated>
		<difficult>0</difficult>
		<bndbox>
			<xmin>37</xmin>
			<ymin>705</ymin>
			<xmax>91</xmax>
			<ymax>773</ymax>
		</bndbox>
	</object>
</annotation>
