<annotation>
	<folder>王心亮</folder>
	<filename>MER2-231-41U3C(FDA19080001)_2020-09-26_15_27_13_255-1098.jpg</filename>
	<path>G:\BaiduNetdiskDownload\王心亮\MER2-231-41U3C(FDA19080001)_2020-09-26_15_27_13_255-1098.jpg</path>
	<source>
		<database>Unknown</database>
	</source>
	<size>
		<width>1920</width>
		<height>1200</height>
		<depth>3</depth>
	</size>
	<segmented>0</segmented>
	<object>
		<name>blue</name>
		<pose>Unspecified</pose>
		<truncated>0</truncated>
		<difficult>0</difficult>
		<bndbox>
			<xmin>627</xmin>
			<ymin>719</ymin>
			<xmax>685</xmax>
			<ymax>789</ymax>
		</bndbox>
	</object>
	<object>
		<name>blue</name>
		<pose>Unspecified</pose>
		<truncated>0</truncated>
		<difficult>0</difficult>
		<bndbox>
			<xmin>206</xmin>
			<ymin>661</ymin>
			<xmax>256</xmax>
			<ymax>712</ymax>
		</bndbox>
	</object>
	<object>
		<name>red</name>
		<pose>Unspecified</pose>
		<truncated>1</truncated>
		<difficult>0</difficult>
		<bndbox>
			<xmin>1</xmin>
			<ymin>892</ymin>
			<xmax>34</xmax>
			<ymax>970</ymax>
		</bndbox>
	</object>
</annotation>
